mbbank_mcp/__init__.py
mbbank_mcp/__main__.py
mbbank_mcp/core.py
mbbank_mcp/modals.py
mbbank_mcp-0.0.7.dist-info/licenses/LICENSE
mbbank_mcp-0.0.7.dist-info/METADATA
mbbank_mcp-0.0.7.dist-info/WHEEL
mbbank_mcp-0.0.7.dist-info/entry_points.txt
mbbank_mcp-0.0.7.dist-info/top_level.txt
mbbank_mcp-0.0.7.dist-info/RECORD
