Metadata-Version: 2.4
Name: mbbank-mcp
Version: 0.0.7
Summary: An MCP server for MBBank using mbbank-lib.
Author-email: The DT <duongtuan30306@gmail.com>
License-Expression: MIT
Project-URL: Homepage, https://github.com/thedtvn/mbbank-mcp
Requires-Python: >=3.10
License-File: LICENSE
Requires-Dist: mcp
Requires-Dist: mbbank-lib
Requires-Dist: click
Requires-Dist: uvicorn
Requires-Dist: starlette
Requires-Dist: qrcode[pil]
Requires-Dist: pillow
Dynamic: license-file
